{"version":1,"stage":1,"attempt":2,"name":"Ideate","systemPrompt":"Frame the task and list 2-3 solution options. Do not edit files.","inputPrompt":"# Relay stage 1: Ideate\nTask: 00c-fix-task-author-read-only\nWorking directory: /Users/admin/Dev/temp-visual-relay/\n\n## Task input\n# Make Fix-Task Authoring Read-Only\n\n## Problem\n\n\u0060FixTaskAuthorRunner\u0060 is described as a read-only prompt-and-parse step:\n\n\u003E No worktree - this is a read-only prompt-and-parse step.\n\nBut its synthetic stage definition currently grants broad capability:\n\n- \u0060Files: \u0022all\u0022\u0060\n- \u0060Commands: \u0022all\u0022\u0060\n\nThat gives the task-authoring model more power than the feature needs. It only needs the failure\ncontext already assembled into the prompt and should return JSON markdown for a new task. It should\nnot be able to edit the repository or execute arbitrary commands.\n\n## Goal\n\nMake \u0022Create task to fix\u0022 authoring genuinely read-only and low-capability while preserving the button\nbehavior and task-writing flow owned by the app.\n\n## What to build\n\n1. Reduce \u0060FixTaskAuthorRunner\u0060 stage capabilities.\n   - Use no write access.\n   - Use no command execution unless a narrowly justified read-only command set is truly necessary.\n   - Prefer passing all needed failure context in the prompt, as it does today.\n2. Keep the app-owned write step unchanged.\n   - The app may still write the returned markdown through \u0060RelayTaskWriter.CreateAsync\u0060 after it\n     validates and disambiguates the slug.\n   - The subagent itself must not write files.\n3. Add tests that inspect the captured \u0060StageInvocation\u0060.\n   - The fix-task author invocation must not use \u0060Files: \u0022all\u0022\u0060 or \u0060Commands: \u0022all\u0022\u0060.\n   - The happy path still creates a new task from returned JSON.\n   - Invalid JSON/error paths still surface a clean status message and write nothing.\n4. Keep the behavior general. Do not add language- or toolchain-specific logic to the authoring path.\n\n## Done criteria\n\n- The fix-task authoring subagent cannot edit files or run arbitrary commands.\n- Existing create-fix-task tests still pass.\n- New capability-scope tests fail before the fix and pass after it.\n- The full \u0060./visual-relay check\u0060 gate passes.\n\n\n## Manifest\n(not set yet)\n\n## Prior stages\n\n\nEnd your reply with a single fenced \u0060\u0060\u0060json block, nothing after it, matching: { \u0022summary\u0022: string, \u0022options\u0022: string[] }","timestamp":"2026-07-01T16:58:55.0189060\u002B00:00"}