{"version":1,"stage":2,"attempt":1,"name":"Research","systemPrompt":"Investigate the codebase; record findings and constraints. Do not edit files.","inputPrompt":"# Relay stage 2: Research\nTask: improve-design-of-live-tiers-section-in-settings\nWorking directory: /Users/nicholaswestby/Dev/visual-relay/\n\n## Task input\n# Improve Design of Live Tiers Section in Settings\n\nThe text is a bit small, the are multiple alignment issues, there is no vertical spacing between dropdowns.\n\nThe text should be the standard sizes used by the rest of the app, the horizontal alignment should be in good taste, and there should be some amount of vertigal gap between the dropdowns.\n\nI\u0027m not sure what the text to the right of each dropdown is (perhaps the API provider), but it doesn\u0027t seem to change on dropdown selection and isn\u0027t configurable, so it should just be removed entirely.\n\n## Manifest\n(not set yet)\n\n## Task context\n### Screenshot 2026-06-30 at 9.12.08\u202FAM.png (24140 bytes, not inlined)\n\n## Prior stages\n## Stage 1 - Ideate\n\n{\n  \u0022summary\u0022: \u0022The Live Tiers section in SettingsPanel.axaml uses font sizes (8-9) far smaller than the rest of the panel (11-16), has zero vertical gap between dropdown rows, uses fragile Auto-width column alignment, and displays a ProviderName column that doesn\u0027t respond to user selection and isn\u0027t configurable. The fix involves updating font sizes to match app standards, adding proper row spacing, improving the grid layout, and removing the non-functional ProviderName column.\u0022,\n  \u0022options\u0022: [\n    \u0022Option A \u2014 Refactor the Live Tiers card with app-standard sizing and clean grid: bump the header to FontSize=13 (subsection heading style), description to 11, ComboBox to 12, and tier labels to 13. Replace the 4-column Auto-width grid with a 3-column layout (dot, tier name, dropdown), removing ProviderName. Change the outer StackPanel Spacing from 1\u21928 and the ItemsPanel Spacing from 0\u21926 so dropdowns have comfortable vertical breathing room. This is the most faithful to the existing card structure while fixing all the stated issues.\u0022,\n    \u0022Option B \u2014 Promote Live Tiers to a full-height section matching \u0027Provider Keys\u0027: give it the same FontSize=16 section header, FontSize=11 sub-text, and a similar bordered-row layout (like each provider key row) with consistent Padding/Margin. Each editable tier becomes a bordered row with a green/gray dot, bold tier name, and ComboBox. This makes the visual hierarchy consistent but requires more layout surface area in the scrollable panel.\u0022,\n    \u0022Option C \u2014 Minimal surgical fix: only change the XAML values (bump FontSize in 6 places, increase Spacing in 2 places, delete the ProviderName TextBlock and its Grid column) without restructuring the layout. Fastest to implement and test, but leaves the overall card feel slightly inconsistent with the rest of the panel since the outer card Padding=4 and tight StackPanel Spacing=1 make it look cramped.\u0022\n  ]\n}\n\n\n\nEnd your reply with a single fenced \u0060\u0060\u0060json block, nothing after it, matching: { \u0022findings\u0022: string, \u0022constraints\u0022: string[] }","timestamp":"2026-06-30T17:56:59.7334870\u002B00:00"}