[
  {
    "stage": 1,
    "name": "Ideate",
    "status": "Done",
    "check": null,
    "durationSeconds": 25.052,
    "costUsd": 0.0011268040000000001,
    "turns": 4,
    "model": "cheap-kimi",
    "error": null
  },
  {
    "stage": 2,
    "name": "Research",
    "status": "Done",
    "check": null,
    "durationSeconds": 76.206,
    "costUsd": 0.0061773712,
    "turns": 13,
    "model": "cheap-kimi",
    "error": null
  },
  {
    "stage": 3,
    "name": "Diagnose",
    "status": "Done",
    "check": null,
    "durationSeconds": 101.762,
    "costUsd": 0.020899024000000002,
    "turns": 16,
    "model": "balanced-kimi",
    "error": null
  },
  {
    "stage": 4,
    "name": "Plan",
    "status": "Done",
    "check": null,
    "durationSeconds": 348.343,
    "costUsd": 0.018661036,
    "turns": 11,
    "model": "balanced-kimi",
    "error": null
  },
  {
    "stage": 5,
    "name": "Author-tests",
    "status": "Done",
    "check": "red",
    "durationSeconds": 237.998,
    "costUsd": 0.019874453999999996,
    "turns": 14,
    "model": "balanced-kimi",
    "error": null
  },
  {
    "stage": 6,
    "name": "Implement",
    "status": "Done",
    "check": null,
    "durationSeconds": 1013.2049999999999,
    "costUsd": 0.051379648,
    "turns": 77,
    "model": "balanced-kimi",
    "error": null
  },
  {
    "stage": 7,
    "name": "Review",
    "status": "Done",
    "check": null,
    "durationSeconds": 400.73400000000004,
    "costUsd": 0.07587920999999999,
    "turns": 8,
    "model": "frontier",
    "error": null
  },
  {
    "stage": 8,
    "name": "Fix",
    "status": "Done",
    "check": null,
    "durationSeconds": 58.873999999999995,
    "costUsd": 0.013685128999999999,
    "turns": 8,
    "model": "balanced-kimi",
    "error": null
  },
  {
    "stage": 9,
    "name": "Verify",
    "status": "Done",
    "check": "green",
    "durationSeconds": 34.96,
    "costUsd": 0.0053129776,
    "turns": 8,
    "model": "cheap-kimi",
    "error": null
  },
  {
    "stage": 10,
    "name": "Fix-verify",
    "status": "Done",
    "check": null,
    "durationSeconds": 113.334,
    "costUsd": 0.016507322,
    "turns": 9,
    "model": "balanced-kimi",
    "error": null
  },
  {
    "stage": 11,
    "name": "Commit",
    "status": "Done",
    "check": null,
    "durationSeconds": 0.0018998,
    "costUsd": 0,
    "turns": null,
    "model": null,
    "error": null
  }
]