{"version":1,"stage":2,"attempt":1,"name":"Research","systemPrompt":"Investigate the codebase; record findings and constraints. Do not edit files.","inputPrompt":"# Relay stage 2: Research\nTask: 05-sandbox-support-for-unity-projects\nWorking directory: /Users/admin/Dev/temp-visual-relay/\n\n## Task input\n# Grant Unity Project Cache \u0026 License Paths in the Sandbox\n\nMake the OS sandboxes stop **blocking Unity\u0027s writes** so a task run on a Unity (C#/.NET) project\ndoes not fail on denied filesystem access. Unity\u0027s editor tooling writes to a handful of global\ncache and license directories that live **outside** the workspace and outside the toolchain-cache\npaths \u0060vr-guard\u0060 currently grants; under the sandbox those writes are denied today.\n\nThis task covers **only the sandbox path grants**, and only on the two OSes that matter for Unity\nhere: **macOS** (nono) and **Windows** (MXC). **Linux is explicitly out of scope** for Unity (project\ndecision). It does **not** make VR detect or drive Unity \u2014 see **Scope / non-goals** below. Keep the\nchanges as small and general as the existing per-ecosystem grants (.NET, Swift, Node, \u2026).\n\n## Current state\n\nVR confines Swival\u0027s writes with two OS sandboxes, both authored in-repo:\n\n- **macOS/Linux \u2014 nono.** Profile \u0060packaging/nono/vr-guard.json\u0060 (\u0060\u0022extends\u0022: \u0022swival\u0022\u0060). The\n  \u0060filesystem.allow\u0060 array is the write/delete allowlist; \u0060filesystem.read\u0060 is \u0060[\u0022/\u0022,\n  \u0022$HOME/.gitconfig\u0022]\u0060 so **reads are already global**. The file is an embedded resource\n  (\u0060VisualRelay.Core.csproj\u0060, \u0060EmbeddedResource Include=\u0022..\\..\\packaging\\nono\\vr-guard.json\u0022\u0060) and is\n  self-healed to the runtime copy at run start by \u0060NonoProfileEnsurer.EnsureAsync\u0060 \u2014 the repo file\n  and the embedded copy are the *same* file, so editing \u0060packaging/nono/vr-guard.json\u0060 and rebuilding\n  \u0060VisualRelay.Core\u0060 is the only edit needed (no second copy to sync). \u0060vr-guard\u0060 extends the pulled\n  \u0060swival\u0060 pack, which pulls in nono\u0027s built-in group \u0060user_caches_macos\u0060 \u2014 it grants **read-write**\n  \u0060~/Library/Caches\u0060 \u002B \u0060~/Library/Logs\u0060 and **read-only** \u0060~/Library/Preferences\u0060.\n- **Windows \u2014 MXC.** \u0060MxcPolicyGenerator.DefaultWindowsCacheDirs()\u0060 returns the read-write cache\n  roots (mirroring vr-guard); \u0060Generate()\u0060 writes them into \u0060filesystem.readwritePaths\u0060. Crucially it\n  returns **only directories that already exist** (a missing path makes MXC container setup fail).\n  \u0060%LOCALAPPDATA%\u0060 and \u0060%APPDATA%\u0060 are granted **wholesale** today.\n\nWhat that means for Unity right now (each macOS verdict below was confirmed with\n\u0060nono why --profile vr-guard --path \u003Cp\u003E --op readwrite\u0060):\n\n| Unity path | OS | Status today | Source |\n|---|---|---|---|\n| \u0060~/Library/Caches/com.unity3d.*\u0060 (GI/shader/editor cache) | macOS | \u2705 writable | group \u0060user_caches_macos\u0060 |\n| \u0060~/Library/Logs/Unity\u0060 | macOS | \u2705 writable | group \u0060user_caches_macos\u0060 |\n| editor binary under \u0060/Applications/Unity/Hub/Editor/\u003Cver\u003E/\u2026\u0060 | macOS | \u2705 readable | group \u0060system_read_macos\u0060 |\n| \u0060~/Library/Unity\u0060 (UPM package cache \u002B \u0060Asset Store-5.x\u0060) | macOS | \u274C **write denied** | only \u0060/\u0060 read |\n| \u0060~/Library/Application Support/Unity\u0060 (licensing client / \u0060.ulf\u0060) | macOS | \u274C **write denied** | only \u0060/\u0060 read |\n| \u0060~/Library/Application Support/UnityHub\u0060 (editor resolution) | macOS | \u274C **write denied** | only \u0060/\u0060 read |\n| \u0060~/Library/Preferences/com.unity3d.*.plist\u0060 (editor prefs) | macOS | \u26A0\uFE0F read-only (write denied) | \u0060user_caches_macos\u0060 grants Preferences read-only |\n| \u0060%LOCALAPPDATA%\\Unity\\*\u0060, \u0060%APPDATA%\\Unity\u0060, \u0060%APPDATA%\\UnityHub\u0060 | Windows | \u2705 writable | wholesale \u0060%LOCALAPPDATA%\u0060/\u0060%APPDATA%\u0060 |\n| \u0060%PROGRAMDATA%\\Unity\u0060 (\u0060C:\\ProgramData\\Unity\u0060, license files) | Windows | \u274C **write denied** | not in \u0060DefaultWindowsCacheDirs()\u0060 |\n\nSo most of Unity\u0027s churn (caches, logs, editor binary reads, and on Windows almost everything) is\nalready permitted. The genuine gaps are the **UPM package cache** and the **license/hub state dirs**\nthat sit outside the cache roots.\n\nWorkspace-local Unity dirs (\u0060Library/\u0060, \u0060Temp/\u0060, \u0060obj/\u0060, \u0060Logs/\u0060, \u0060Build/\u0060) are inside the granted\nworkspace (writable via \u0060--allow-cwd\u0060) and \u2014 because a standard Unity \u0060.gitignore\u0060 ignores them and\nthey are large \u2014 are already excluded from nono\u0027s ~2 GiB rollback preflight by the **existing general\nmechanism** \u0060NonoRollbackSkipDirs.ComputeAsync\u0060 (skips top-level git-ignored dirs \u2265256 MB via\n\u0060--skip-dir\u0060). No new code is expected there; see the verification note under **What to build**.\n\n## What to build\n\n### 1. nono profile \u2014 \u0060packaging/nono/vr-guard.json\u0060\n\nAdd the missing macOS write grants to \u0060filesystem.allow\u0060, following the file\u0027s existing conventions:\n\u0060$HOME\u0060-relative, and \u0060{ \u0022path\u0022: \u2026, \u0022when\u0022: \u0022macos\u0022 }\u0060 predicates for OS-specific paths (hardcoded\n\u0060/Users/\u2026\u0060 is rejected by a test). Group them with a short comment near the other toolchain blocks.\nAdd:\n\n- \u0060{ \u0022path\u0022: \u0022$HOME/Library/Unity\u0022, \u0022when\u0022: \u0022macos\u0022 }\u0060 \u2014 UPM global package cache \u002B \u0060Asset Store-5.x\u0060\n- \u0060{ \u0022path\u0022: \u0022$HOME/Library/Application Support/Unity\u0022, \u0022when\u0022: \u0022macos\u0022 }\u0060 \u2014 licensing client state / \u0060.ulf\u0060\n- \u0060{ \u0022path\u0022: \u0022$HOME/Library/Application Support/UnityHub\u0022, \u0022when\u0022: \u0022macos\u0022 }\u0060 \u2014 Unity Hub (editor resolution)\n\nDo **not** add: any Linux (\u0060when: \u0022linux\u0022\u0060) Unity paths (out of scope); \u0060~/Library/Caches/*\u0060 or\n\u0060~/Library/Logs/*\u0060 (already granted by \u0060user_caches_macos\u0060); any \u0060read:\u0060 entries (reads are already\nglobal); or a broad \u0060~/Library/Preferences\u0060 **write** \u2014 that would open every app\u0027s prefs. The\nread-only Preferences limitation (editor prefs won\u0027t persist across sandboxed runs) is acceptable for\nbatch/CI runs and is explicitly out of scope; leave a one-line comment noting it rather than widening\nthe grant.\n\n### 2. nono rollback exclusions \u2014 same file, \u0060rollback.exclude_patterns\u0060\n\nThe newly-granted \u0060~/Library/Unity\u0060 (UPM cache) can be multiple GB; nono\u0027s rollback preflight\nsnapshots every writable path, so it must be excluded or it blows the fixed budget. Add the pattern:\n\n- \u0060\u0022Unity\u0022\u0060\n\n**Landmine \u2014 do NOT add \u0060\u0022Library\u0022\u0060.** These patterns match a path component/substring, so \u0060\u0022Library\u0022\u0060\nwould match \u0060~/Library\u0060 (disabling rollback for the whole macOS Library tree) **and** the Unity\nproject\u0027s own workspace \u0060Library/\u0060 folder. \u0060\u0022Unity\u0022\u0060 is specific: it covers \u0060~/Library/Unity\u0060,\n\u0060~/Library/Application Support/Unity\u0060, and \u0060~/Library/Application Support/UnityHub\u0060, without matching\n\u0060~/Library\u0060 or the lowercase \u0060com.unity3d.*\u0060 caches (already excluded via the existing \u0060\u0022Caches\u0022\u0060\npattern).\n\n### 3. Windows MXC \u2014 \u0060MxcPolicyGenerator.DefaultWindowsCacheDirs()\u0060\n\nThe wholesale \u0060%LOCALAPPDATA%\u0060/\u0060%APPDATA%\u0060 grants already cover Unity\u0027s Windows cache, logs, Asset\nStore, and Hub dirs. The one gap is the shared license dir. Add:\n\n- \u0060Path.Combine(Environment.GetFolderPath(Environment.SpecialFolder.CommonApplicationData), \u0022Unity\u0022)\u0060\n  \u2014 i.e. \u0060C:\\ProgramData\\Unity\u0060\n\nAdd it to the \u0060dirs\u0060 list *before* the existing \u0060.Where(d =\u003E \u2026 \u0026\u0026 Directory.Exists(d))\u0060 filter so a\nhost without Unity installed simply drops it (mirrors how \u0060~/.cargo\u0060 is handled). Do **not** add bare\n\u0060%PROGRAMDATA%\u0060 (over-broad).\n\n### 4. Verify the workspace-local rollback skip (expected: no change)\n\nConfirm \u0060NonoRollbackSkipDirs\u0060 already keeps a Unity project\u0027s git-ignored \u0060Library/\u0060/\u0060Temp/\u0060 out of\nrollback preflight (they must be git-ignored \u2014 the standard Unity \u0060.gitignore\u0060 does this \u2014 and \u2265256 MB\nto trip the size gate). If a realistic Unity project would still blow the budget, note it, but do not\nspecial-case Unity by name here \u2014 the mechanism is intentionally ecosystem-agnostic.\n\n### 5. Recommended empirical validation\n\nThe macOS path list above is the known default, not gospel \u2014 Unity\u0027s exact cache locations vary by\nversion. Validate against a real Unity project before finalizing:\n\n- Query the live policy: \u0060nono why --profile vr-guard --path \u003Cp\u003E --op readwrite --json\u0060.\n- Or, without editing the profile, drop the candidate paths into a Unity repo\u0027s \u0060.relay/config.json\u0060\n  \u0060sandboxExtraAllowPaths\u0060 (they map straight to nono \u0060-a \u003Cpath\u003E\u0060 via\n  \u0060SwivalSubagentRunner.BuildNonoPrefix\u0060; validated in \u0060RelayConfigLoader\u0060 \u2014 all are under \u0060$HOME\u0060 and\n  none are in its sensitive-subtree denylist) and run a real editor task to see what\u0027s actually hit.\n\n## Scope / non-goals\n\nThis task is the **sandbox slice only**. It makes the sandbox stop blocking Unity; it does **not**\nmake VR recognize or run Unity projects. Out of scope (separate future tasks \u2014 do not start them here,\nand do not let their absence block this one): a Unity-priority detector branch in\n\u0060TestCommandDetector.DetectCandidates\u0060 (today a Unity project matches the generic \u0060*.csproj\u0060/\u0060*.sln\u0060\nbranch and resolves \u0060dotnet test\u0060, which cannot drive Unity); a Unity batch-mode test/build command\nwith editor-path resolution off \u0060ProjectSettings/ProjectVersion.txt\u0060; and Unity licensing activation\n(granting write to the license dirs here is necessary but not sufficient). **Linux Unity support is\nalso out of scope.** Because those pieces don\u0027t exist yet, this task\u0027s changes are **safe and inert**\nfor non-Unity projects (existence-filtered on Windows; extra allow entries only matter when Unity\nactually runs).\n\n## Constraints \u0026 done criteria\n\n- **Tests.** Mirror the existing per-toolchain structure tests:\n  - Add \u0060VrGuardProfile_HasUnityEntries\u0060 to \u0060tests/VisualRelay.Tests/NonoProfileStructureTests.cs\u0060\n    (same shape as \u0060VrGuardProfile_HasDotNetEntries\u0060/\u0060HasSwiftEntries\u0060 using the \u0060CollectPaths\u0060 helper).\n  - Extend \u0060VrGuardProfileRollbackTests.VrGuardProfile_ExcludesLargeToolchainCaches_FromRollback\u0060\n    (\u0060tests/VisualRelay.Tests/VrGuardProfileRollbackTests.cs\u0060) to require \u0060\u0022Unity\u0022\u0060.\n  - The existing \u0060VrGuardProfile_HasWhenPredicatesForOsSpecificPaths\u0060 and the no-hardcoded-\u0060/Users/\u0060\n    check (\u0060VrGuardProfile_HasFilesystemAllowEntries\u0060) must still pass \u2014 use \u0060when\u0060 predicates and\n    \u0060$HOME\u0060, never literal paths.\n  - If a Windows-side structure/existence test exists for \u0060DefaultWindowsCacheDirs()\u0060, extend it; the\n    existence-filter must keep a Unity-less host clean.\n- **Stay general.** No Unity-version-specific hardcoding beyond the stable dir names; harmless when\n  Unity is absent.\n- Keep every new/edited \u0060*.cs\u0060 file \u2264 300 lines (VR\u0027s file-size guard); do not weaken, skip, or delete\n  any test.\n- Full \u0060Verify\u0060 gate green (\u0060Failed: 0\u0060, exit 0).\n\n## Files likely in scope (the plan stage will finalize the manifest)\n\n- \u0060packaging/nono/vr-guard.json\u0060 \u2014 \u0060filesystem.allow\u0060 (macOS Unity grants) \u002B \u0060rollback.exclude_patterns\u0060 (\u0060\u0022Unity\u0022\u0060)\n- \u0060src/VisualRelay.Core/Execution/MxcPolicyGenerator.cs\u0060 \u2014 \u0060DefaultWindowsCacheDirs()\u0060 adds \u0060C:\\ProgramData\\Unity\u0060\n- \u0060tests/VisualRelay.Tests/NonoProfileStructureTests.cs\u0060 \u2014 new \u0060VrGuardProfile_HasUnityEntries\u0060\n- \u0060tests/VisualRelay.Tests/VrGuardProfileRollbackTests.cs\u0060 \u2014 require \u0060\u0022Unity\u0022\u0060 exclusion\n- possibly a Windows \u0060MxcPolicyGenerator\u0060 test, if one exists\n- (verify only, likely no change) \u0060src/VisualRelay.Core/Execution/NonoRollbackSkipDirs.cs\u0060\n\n\n## Manifest\n(not set yet)\n\n## Prior stages\n## Stage 1 - Ideate\n\n{\n  \u0022summary\u0022: \u0022Add sandbox path grants for Unity\u0027s global cache and license directories on macOS (nono profile vr-guard.json: 3 paths in filesystem.allow \u002B \u0027Unity\u0027 in rollback.exclude_patterns) and Windows (MxcPolicyGenerator: C:\\\\ProgramData\\\\Unity). Add corresponding structure and rollback tests. Follow existing per-toolchain conventions ($HOME-relative, \u0027when: macos\u0027 predicates, existence-filtered on Windows). Leave Preferences read-only as acceptable for CI/batch.\u0022,\n  \u0022options\u0022: [\n    \u0022Option 1 \u2014 Strict compliance: exactly the 3 macOS paths, 1 Windows path, 1 rollback exclusion, and matching tests as specified. Follows existing convention, minimal diff, safe.\u0022,\n    \u0022Option 2 \u2014 Wildcard macOS Application Support: consolidate Unity and UnityHub into a single \u0027Unity*\u0027 glob entry. Fewer entries but breaks pattern of explicit per-path grants used by other toolchains.\u0022,\n    \u0022Option 3 \u2014 Also grant Unity-specific Preferences write: add write for ~/Library/Preferences/com.unity3d.*.plist. More complete Unity UX but deviates from spec\u0027s explicit non-goal; acceptable for a future follow-up.\u0022\n  ]\n}\n\n\n\nEnd your reply with a single fenced \u0060\u0060\u0060json block, nothing after it, matching: { \u0022findings\u0022: string, \u0022constraints\u0022: string[] }","timestamp":"2026-07-01T09:38:50.5900880\u002B00:00"}